bbai-1.16.0.dist-info/METADATA
bbai-1.16.0.dist-info/RECORD
bbai-1.16.0.dist-info/WHEEL
bbai//__init__.py
bbai//_computation/__init__.py
bbai//_computation/_bridge.py
bbai//bbai
bbai//glm/__init__.py
bbai//glm/_bayesian_logistic_regression1.py
bbai//glm/_bayesian_ridge_regression.py
bbai//glm/_lasso.py
bbai//glm/_lasso_validate.py
bbai//glm/_logistic_regression.py
bbai//glm/_logistic_regression_map.py
bbai//glm/_loss_link.py
bbai//glm/_random_dataset.py
bbai//glm/_ridge_regression.py
bbai//glm/posterior_equations.py
bbai//gp/__init__.py
bbai//gp/_bayesian_gaussian_process_regression.py
bbai//gp/_bayesian_regression_pdfs.py
bbai//gp/_covariance_function.py
bbai//gp/_gaussian_process_regression_map.py
bbai//gp/_marginal.py
bbai//gp/_marginal_regressor.py
bbai//gp/_marginal_sigma2_signal.py
bbai//gp/_problem_validation.py
bbai//gp/_regression_map_pdf.py
bbai//gp/reference_equations.py
bbai//graphics/__init__.py
bbai//graphics/_bezier.py
bbai//metric/__init__.py
bbai//metric/_gaussian_kl.py
bbai//model/__init__.py
bbai//model/_binomial_hypothesis.py
bbai//model/_bounded_normal.py
bbai//model/_delta_binomial.py
bbai//model/_restricted_t.py
bbai//numeric/__init__.py
bbai//numeric/_sparse_grid.py
bbai//plot/__init__.py
bbai//plot/_errors.py
bbai//poly/__init__.py
bbai//poly/_interpolation.py
bbai//poly/_marginalization.py
bbai//quad/__init__.py
bbai//quad/_grid.py
bbai//quad/_interpolation.py
bbai//stat/__init__.py
bbai//stat/_normal_mean_hypothesis.py
bbai/LICENSE
bbai/third_party/license/abseil/LICENSE
bbai/third_party/license/fmtlib/LICENSE.rst
bbai/third_party/license/mkl/intel-simplified-software-license.pdf
bbai/third_party/license/tbb/LICENSE
