Metadata-Version: 2.1
Name: bbai
Version: 1.16.0
Author: Ryan Burn
Author-email: ryan.burn@gmail.com
Home-page: http://buildingblock.ai
License: CC0 4.0
Summary: Efficiently and precisely tune model parameters
Platform: UNKNOWN
Classifier: Operating System :: OS Independent
Classifier: Programming Language :: Python
Classifier: Programming Language :: Python :: 2
Classifier: Programming Language :: Python :: 2.7
Classifier: Programming Language :: Python :: 3
Classifier: Topic :: Scientific/Engineering :: Mathematics
Classifier: Topic :: Scientific/Engineering :: Artificial Intelligence
Requires-Python: >=2.7
Requires-Dist: numpy (>=1.0.0)
Requires-Dist: scipy (>=1.0.0)
Requires-Dist: greenlet (>=1.0.0)
